README.md
setup.py
asyn_task/__init__.py
asyn_task/daemon.py
asyn_task/log.py
asyn_task.egg-info/PKG-INFO
asyn_task.egg-info/SOURCES.txt
asyn_task.egg-info/dependency_links.txt
asyn_task.egg-info/entry_points.txt
asyn_task.egg-info/requires.txt
asyn_task.egg-info/top_level.txt